collective.restrictportlets-1.0.0-py2.7-nspkg.pth
collective/restrictportlets/__init__.py
collective/restrictportlets/configure.zcml
collective/restrictportlets/controlpanel.py
collective/restrictportlets/interfaces.py
collective/restrictportlets/patches.py
collective/restrictportlets/setuphandlers.py
collective/restrictportlets/testing.py
collective/restrictportlets/locales/collective.restrictportlets.pot
collective/restrictportlets/locales/update.sh
collective/restrictportlets/locales/nl/LC_MESSAGES/collective.restrictportlets.mo
collective/restrictportlets/locales/nl/LC_MESSAGES/collective.restrictportlets.po
collective/restrictportlets/profiles/default/browserlayer.xml
collective/restrictportlets/profiles/default/controlpanel.xml
collective/restrictportlets/profiles/default/metadata.xml
collective/restrictportlets/profiles/default/registry.xml
collective/restrictportlets/profiles/uninstall/browserlayer.xml
collective/restrictportlets/profiles/uninstall/controlpanel.xml
collective/restrictportlets/profiles/uninstall/registry.xml
collective/restrictportlets/tests/__init__.py
collective/restrictportlets/tests/test_patch.py
collective/restrictportlets/tests/test_setup.py
collective.restrictportlets-1.0.0.dist-info/LICENSE.GPL
collective.restrictportlets-1.0.0.dist-info/LICENSE.rst
collective.restrictportlets-1.0.0.dist-info/METADATA
collective.restrictportlets-1.0.0.dist-info/WHEEL
collective.restrictportlets-1.0.0.dist-info/entry_points.txt
collective.restrictportlets-1.0.0.dist-info/namespace_packages.txt
collective.restrictportlets-1.0.0.dist-info/top_level.txt
collective.restrictportlets-1.0.0.dist-info/RECORD
