Metadata-Version: 2.1
Name: collective.restrictportlets
Version: 1.0.0
Summary: Restrict addable portlet types
Home-page: https://github.com/collective/collective.restrictportlets
Author: Maurits van Rees
Author-email: m.van.rees@zestsoftware.nl
License: GPL version 2
Keywords: Python Plone
Platform: UNKNOWN
Classifier: Development Status :: 5 - Production/Stable
Classifier: Environment :: Web Environment
Classifier: Framework :: Plone
Classifier: Framework :: Plone :: 4.3
Classifier: Framework :: Plone :: 5.0
Classifier: Framework :: Plone :: 5.1
Classifier: Framework :: Plone :: 5.2
Classifier: Framework :: Plone :: 6.0
Classifier: Programming Language :: Python
Classifier: Programming Language :: Python :: 2.7
Classifier: Programming Language :: Python :: 3.6
Classifier: Programming Language :: Python :: 3.7
Classifier: Programming Language :: Python :: 3.8
Classifier: Programming Language :: Python :: 3.9
Classifier: Operating System :: OS Independent
Classifier: License :: OSI Approved :: GNU General Public License v2 (GPLv2)
Requires-Dist: collective.monkeypatcher
Requires-Dist: plone.api
Requires-Dist: plone.app.registry
Requires-Dist: Products.GenericSetup
Requires-Dist: setuptools
Provides-Extra: test
Requires-Dist: plone.app.testing ; extra == 'test'
Requires-Dist: plone.testing (>=5.0.0) ; extra == 'test'
